omen/__init__.py
omen-1.4.dist-info/DESCRIPTION.rst
omen-1.4.dist-info/METADATA
omen-1.4.dist-info/RECORD
omen-1.4.dist-info/WHEEL
omen-1.4.dist-info/metadata.json
omen-1.4.dist-info/top_level.txt
omen-1.4.dist-info/zip-safe
