Metadata-Version: 2.0
Name: omen
Version: 1.4
Summary: Simple markov chain library
Home-page: https://github.com/veggiedefender/omen
Author: Jesse Li
Author-email: jessejesse123@gmail.com
License: MIT
Keywords: markov chain nlp
Platform: UNKNOWN
Requires-Dist: nltk
Requires-Dist: dill
